{
  "schemes" : [
    {
      "scrolling" : {
        "reverse" : {
          "vertical" : true,
          "horizontal" : false
        },
        "distance" : 3
      },
      "buttons" : {
        "universalBackForward" : true
      },
      "pointer" : {
        "speed" : 0.2965517241379308544,
        "acceleration" : 0,
        "disableAcceleration" : false
      },
      "if" : {
        "device" : {
          "productID" : "0x88",
          "productName" : "Razer Basilisk Ultimate Dongle",
          "category" : "mouse",
          "vendorID" : "0x1532"
        }
      }
    },
    {
      "if" : {
        "device" : {
          "productName" : "Razer Basilisk Ultimate Dongle",
          "vendorID" : "0x1532",
          "category" : "mouse",
          "productID" : "0x88"
        },
        "app" : "org.mozilla.firefox"
      },
      "scrolling" : {
        "distance" : 7
      }
    },
    {
      "if" : {
        "device" : {
          "productName" : "Apple Internal Keyboard \/ Trackpad",
          "category" : "trackpad",
          "productID" : "0x343",
          "vendorID" : "0x5ac"
        }
      },
      "scrolling" : {
        "distance" : "auto"
      }
    },
    {
      "if" : {
        "device" : {
          "vendorID" : "0x3297",
          "productName" : "Moonlander Mark I",
          "category" : "mouse",
          "productID" : "0x1969"
        }
      },
      "scrolling" : {
        "distance" : 6,
        "reverse" : {
          "horizontal" : false,
          "vertical" : true
        }
      }
    },
    {
      "pointer" : {
        "acceleration" : 0.9,
        "disableAcceleration" : true
      },
      "scrolling" : {
        "modifiers" : {
          "vertical" : {
            "shift" : {
              "type" : "changeSpeed",
              "scale" : 3.5
            }
          }
        },
        "acceleration" : {
          "vertical" : 1
        },
        "distance" : {
          "vertical" : 3
        },
        "speed" : {
          "vertical" : 0
        },
        "reverse" : {
          "vertical" : true
        }
      },
      "if" : {
        "device" : {
          "category" : "mouse",
          "productName" : "USB Receiver",
          "vendorID" : "0x46d",
          "productID" : "0xc539"
        }
      }
    }
  ],
  "$schema" : "https:\/\/schema.linearmouse.app\/0.9.5"
}